vjmail/__init__.py
vjmail/vjmail.py
vjmail-1.1.dist-info/METADATA
vjmail-1.1.dist-info/WHEEL
vjmail-1.1.dist-info/top_level.txt
vjmail-1.1.dist-info/RECORD
