Metadata-Version: 2.1
Name: vjmail
Version: 1.1
Summary: A simple library to centralize VJBots e-mails sendings.
Home-page: https://github.com/Fioruci/vjmail
Author: Fioruci
Author-email: fiorucit@example.com
Classifier: Programming Language :: Python :: 3
Classifier: License :: OSI Approved :: MIT License
Classifier: Operating System :: OS Independent
Requires-Python: >=3.12
